virtuous/__init__.py
virtuous/loader.py
virtuous-0.0.7.dist-info/METADATA
virtuous-0.0.7.dist-info/WHEEL
virtuous-0.0.7.dist-info/top_level.txt
virtuous-0.0.7.dist-info/RECORD
