Metadata-Version: 2.4
Name: virtuous
Version: 0.0.7
Summary: Runtime loader for Virtuous Python clients
License: MIT
Requires-Python: >=3.12
